{
    "makerid":3419,
    "published_date":"2024-07-02 02:01:59.561669",
    "type":"maker",
    "displayname":"Augustin Saint-Aubin",
    "makertype":"Individual",
    "alphasort":"Saint-Aubin Augustin",
    "lastname":"Saint-Aubin",
    "firstname":"Augustin",
    "nametitle":null,
    "middlename":null,
    "suffix":null,
    "displaybio":"1736–1807; born and died Paris, France",
    "begindate":1736,
    "enddate":1807,
    "nationality":"French",
    "culturegroup":null,
    "biography":null,
    "altnames":[
        {
            "nametype":"Primary Name",
            "displayname":"Augustin Saint-Aubin",
            "alphasort":"Saint-Aubin Augustin",
            "lastname":"Saint-Aubin",
            "firstname":"Augustin",
            "nametitle":null,
            "middlename":null,
            "suffix":null,
            "culturegroup":null
        }
    ],
    "identifiers":[],
    "audio":[],
    "video":[],
    "essay":[]
}