{
    "makerid":1049,
    "published_date":"2022-03-28 16:03:55.428891",
    "type":"maker",
    "displayname":"Chen Shuhua 陳樹華",
    "makertype":"Individual",
    "alphasort":"Chen Shuhua",
    "lastname":"Chen Shuhua",
    "firstname":null,
    "nametitle":null,
    "middlename":null,
    "suffix":null,
    "displaybio":null,
    "begindate":1644,
    "enddate":1912,
    "nationality":"Chinese",
    "culturegroup":null,
    "biography":null,
    "altnames":[
        {
            "nametype":"Primary Name",
            "displayname":"Chen Shuhua 陳樹華",
            "alphasort":"Chen Shuhua",
            "lastname":"Chen Shuhua",
            "firstname":null,
            "nametitle":null,
            "middlename":null,
            "suffix":null,
            "culturegroup":null
        },
        {
            "nametype":"Alternate",
            "displayname":"Ch'en Shu-hua",
            "alphasort":"Ch'en Shu-hua",
            "lastname":"Ch'en Shu-hua",
            "firstname":null,
            "nametitle":null,
            "middlename":null,
            "suffix":null,
            "culturegroup":null
        },
        {
            "nametype":"Alternate",
            "displayname":"陳樹華",
            "alphasort":"陳樹華",
            "lastname":"陳樹華",
            "firstname":null,
            "nametitle":null,
            "middlename":null,
            "suffix":null,
            "culturegroup":null
        }
    ],
    "identifiers":[],
    "audio":[],
    "video":[],
    "essay":[]
}