{
    "makerid":121,
    "published_date":"2022-03-28 16:03:20.576101",
    "type":"maker",
    "displayname":"Jacopo d' Antonello",
    "makertype":"Individual",
    "alphasort":"Antonello, Jacopo d'",
    "lastname":"Antonello",
    "firstname":"Jacopo",
    "nametitle":null,
    "middlename":"d'",
    "suffix":null,
    "displaybio":"Italian, fl. 1480 - 1490",
    "begindate":1480,
    "enddate":1490,
    "nationality":"Italian",
    "culturegroup":null,
    "biography":null,
    "altnames":[
        {
            "nametype":"Alternate",
            "displayname":"Jacopo di Antonello",
            "alphasort":"di Antonello, Jacopo",
            "lastname":"di Antonello",
            "firstname":"Jacopo",
            "nametitle":null,
            "middlename":null,
            "suffix":null,
            "culturegroup":null
        },
        {
            "nametype":"Alternate",
            "displayname":"Jacobello d'Antonello",
            "alphasort":"d'Antonello, Jacobello",
            "lastname":"d'Antonello",
            "firstname":"Jacobello",
            "nametitle":null,
            "middlename":null,
            "suffix":null,
            "culturegroup":null
        },
        {
            "nametype":"Alternate",
            "displayname":"Jacobello da Messina",
            "alphasort":"da Messina, Jacobello",
            "lastname":"da Messina",
            "firstname":"Jacobello",
            "nametitle":null,
            "middlename":null,
            "suffix":null,
            "culturegroup":null
        },
        {
            "nametype":"Primary Name",
            "displayname":"Jacopo d' Antonello",
            "alphasort":"Antonello, Jacopo d'",
            "lastname":"Antonello",
            "firstname":"Jacopo",
            "nametitle":null,
            "middlename":"d'",
            "suffix":null,
            "culturegroup":null
        }
    ],
    "identifiers":[],
    "audio":[],
    "video":[],
    "essay":[]
}