{
    "makerid":3483,
    "published_date":"2022-03-28 16:05:29.891452",
    "type":"maker",
    "displayname":"Hans Leonhard Schäufelein",
    "makertype":"Individual",
    "alphasort":"Schäufelein, Hans Leonhard",
    "lastname":"Schäufelein",
    "firstname":"Hans Leonhard",
    "nametitle":null,
    "middlename":null,
    "suffix":null,
    "displaybio":"ca. 1482–1540",
    "begindate":1482,
    "enddate":1540,
    "nationality":"German",
    "culturegroup":null,
    "biography":null,
    "altnames":[
        {
            "nametype":"Primary Name",
            "displayname":"Hans Leonhard Schäufelein",
            "alphasort":"Schäufelein, Hans Leonhard",
            "lastname":"Schäufelein",
            "firstname":"Hans Leonhard",
            "nametitle":null,
            "middlename":null,
            "suffix":null,
            "culturegroup":null
        },
        {
            "nametype":"Alternate",
            "displayname":"Hans Schäufelein the elder",
            "alphasort":"Schäufelein, Hans the elder",
            "lastname":"Schäufelein",
            "firstname":"Hans",
            "nametitle":null,
            "middlename":null,
            "suffix":"the elder",
            "culturegroup":null
        }
    ],
    "identifiers":[],
    "audio":[],
    "video":[],
    "essay":[]
}