{
    "makerid":18505,
    "published_date":"2025-10-10 02:04:57.707267",
    "type":"maker",
    "displayname":"Purépecha",
    "makertype":"Cultural Group",
    "alphasort":"Purépecha",
    "lastname":null,
    "firstname":null,
    "nametitle":null,
    "middlename":null,
    "suffix":null,
    "displaybio":null,
    "begindate":0,
    "enddate":0,
    "nationality":null,
    "culturegroup":"Tarascan",
    "biography":null,
    "altnames":[
        {
            "nametype":"Primary Name",
            "displayname":"Purépecha",
            "alphasort":"Purépecha",
            "lastname":null,
            "firstname":null,
            "nametitle":null,
            "middlename":null,
            "suffix":null,
            "culturegroup":"Tarascan"
        },
        {
            "nametype":null,
            "displayname":"Tarascan",
            "alphasort":"Tarascan",
            "lastname":"Tarascan",
            "firstname":null,
            "nametitle":null,
            "middlename":null,
            "suffix":null,
            "culturegroup":null
        },
        {
            "nametype":null,
            "displayname":"Purepecha",
            "alphasort":"Purepecha",
            "lastname":"Purepecha",
            "firstname":null,
            "nametitle":null,
            "middlename":null,
            "suffix":null,
            "culturegroup":null
        }
    ],
    "identifiers":[
        {
            "source":"AAT",
            "id":"300017783"
        }
    ],
    "audio":[],
    "video":[],
    "essay":[]
}