{
    "type":"artobject",
    "objectid":36643,
    "objectnumber":"1998-358",
    "sortnumber":"1998  358",
    "displaytitle":"Six linked bracelets",
    "department":"Ancient, Byzantine, and Islamic Art",
    "classification":"Metal",
    "datebegin":-800,
    "dateend":-401,
    "datecomputed":-600,
    "daterange":"1000 B.C.-A.D 1",
    "displaydate":"8th century – 5th century BCE",
    "medium":"Bronze",
    "dimensions":"each: diam. 9.4 cm. (3 11/16 in.)",
    "dimensionsproposed":"",
    "creditline":"Bequest of John B. Elliott, Class of 1951",
    "markings":null,
    "inscribed":null,
    "signed":null,
    "catalograisonne":null,
    "creditlinerepro":null,
    "restrictions":null,
    "nowebuse":"False",
    "secondaryobjectnumber":null,
    "campuscollections":"false",
    "on_view":false,
    "accessionyear":"1998-01-01",
    "newaccession":0,
    "titles":[
        {
            "title":"Six linked bracelets",
            "titletype":"Primary Title",
            "displayorder":1
        }
    ],
    "makers":[],
    "depicted":[],
    "texts":[
        {
            "texttype":"Online",
            "textpurpose":"Provenance",
            "textentryhtml":"Formerly in the Pfeffer collection; formerly in the collection of Dr. S. Egger (Vienna); formerly in the Pitt-Rivers collection (Dorset); acquired by Michael Ward at an unknown date from an unknown source; purchased by John B. Elliott, Class of 1951, in 1990 from Ward; bequeathed to the Museum in 1998 by Elliott.\n",
            "remarks":null
        }
    ],
    "media":[
        {
            "id":40104,
            "uri":"https://media.artmuseum.princeton.edu/iiif/3/collection/INV005169",
            "isprimary":1,
            "rank":1,
            "mediatypeid":1,
            "mediaviewtype":"(not assigned)",
            "restrictions":null,
            "caption":"Inventory Project"
        }
    ],
    "hasimage":"true",
    "bibliography":[],
    "exhibitions":[],
    "geography":[
        {
            "displaygeography":"Place excavated: Hungary",
            "code":"Place excavated",
            "continent":null,
            "subcontinent":null,
            "country":"Hungary",
            "region":null,
            "state":null,
            "city":null,
            "county":null,
            "subregion":null,
            "locale":null,
            "locus":null,
            "river":null,
            "excavation":null,
            "geoname":null,
            "location":{
                "lat":"",
                "lon":""
            }
        }
    ],
    "terms":[
        {
            "id":2130789,
            "term":"bracelets (jewelry)",
            "aatid":300045991,
            "termtype":"Classification"
        },
        {
            "id":2036358,
            "term":"European Bronze Age styles and periods",
            "aatid":300019358,
            "termtype":"Period / Style"
        }
    ],
    "classifications":[
        {
            "id":2130789,
            "classification":"bracelets (jewelry)"
        }
    ],
    "cultures":[],
    "cultureterms":[],
    "periods":[
        {
            "id":12596,
            "period":"Bronze Age",
            "alphasort":"Bronze Age",
            "begindate":-3300,
            "enddate":-600,
            "displayperiod":"Bronze Age",
            "displaydate":null
        }
    ],
    "periodterms":[
        {
            "id":2036358,
            "period":"European Bronze Age styles and periods"
        }
    ],
    "dimensionelements":[
        {
            "element":"Overall",
            "type":"diam.",
            "units":"centimeters",
            "dimension":"9.40"
        }
    ],
    "packages":[],
    "primaryimage":[
        "https://media.artmuseum.princeton.edu/iiif/3/collection/INV005169"
    ],
    "displaymaker":null,
    "displayculture":null,
    "displayperiod":"Bronze Age",
    "caption":"Bronze Age, Hungary, 8th century – 5th century BCE, Six linked bracelets. Bronze; 9.4 cm (each). Bequest of John B. Elliott, Class of 1951 (1998-358)",
    "captionhtml":"Bronze Age, Hungary, 8th century – 5th century BCE, <i>Six linked bracelets</i>. Bronze; 9.4 cm (each). Bequest of John B. Elliott, Class of 1951 (1998-358)",
    "published_date":"2025-10-16 13:54:21.333941",
    "campusart":[
        {
            "campuscollections":"false",
            "campusart":0,
            "neighborhood":null,
            "lat":null,
            "lon":null
        }
    ],
    "extended_content":false
}