{
    "type":"artobject",
    "objectid":27838,
    "objectnumber":"y1959-4",
    "sortnumber":"1959    4y",
    "displaytitle":"Bowl",
    "department":"Ancient, Byzantine, and Islamic Art",
    "classification":"Metal",
    "datebegin":0,
    "dateend":1958,
    "datecomputed":null,
    "daterange":"",
    "displaydate":null,
    "medium":"Bronze",
    "dimensions":"3.8 × diam. 15 cm (1 1/2 × 5 7/8 in.)",
    "dimensionsproposed":"",
    "creditline":"Museum purchase",
    "markings":null,
    "inscribed":null,
    "signed":null,
    "catalograisonne":null,
    "creditlinerepro":null,
    "restrictions":null,
    "nowebuse":"False",
    "secondaryobjectnumber":null,
    "campuscollections":"false",
    "on_view":false,
    "accessionyear":"1959-01-01",
    "newaccession":0,
    "titles":[
        {
            "title":"Bowl",
            "titletype":"Primary Title",
            "displayorder":1
        }
    ],
    "makers":[],
    "depicted":[],
    "texts":[
        {
            "texttype":"Online",
            "textpurpose":"Provenance",
            "textentryhtml":"Acquired by H. D. Motamed at an unknown date from an unknown source; purchased by the Museum in 1959 from Motamed.",
            "remarks":null
        }
    ],
    "media":[
        {
            "id":147998,
            "uri":"https://media.artmuseum.princeton.edu/iiif/3/collection/INV65758",
            "isprimary":1,
            "rank":1,
            "mediatypeid":1,
            "mediaviewtype":"(not assigned)",
            "restrictions":null,
            "caption":"Inventory Project"
        },
        {
            "id":147999,
            "uri":"https://media.artmuseum.princeton.edu/iiif/3/collection/INV65759",
            "isprimary":0,
            "rank":2,
            "mediatypeid":1,
            "mediaviewtype":"(not assigned)",
            "restrictions":null,
            "caption":"Inventory Project"
        }
    ],
    "hasimage":"true",
    "bibliography":[],
    "exhibitions":[],
    "geography":[],
    "terms":[
        {
            "id":2134003,
            "term":"lotus",
            "aatid":null,
            "termtype":"Subject"
        },
        {
            "id":2073090,
            "term":"bowls (vessels)",
            "aatid":300203596,
            "termtype":"Classification"
        },
        {
            "id":2037509,
            "term":"Persian",
            "aatid":300019933,
            "termtype":"Culture"
        },
        {
            "id":2037546,
            "term":"Achaemenid",
            "aatid":300019946,
            "termtype":"Period / Style"
        },
        {
            "id":2159399,
            "term":"palmettes",
            "aatid":300009995,
            "termtype":"Subject"
        },
        {
            "id":2159470,
            "term":"rosettes",
            "aatid":300009972,
            "termtype":"Subject"
        }
    ],
    "classifications":[
        {
            "id":2073090,
            "classification":"bowls (vessels)"
        }
    ],
    "cultures":[],
    "cultureterms":[
        {
            "id":2037509,
            "culture":"Persian"
        }
    ],
    "periods":[
        {
            "id":13446,
            "period":"Achaemenid Persian Period",
            "alphasort":"Achaemenid",
            "begindate":-550,
            "enddate":-330,
            "displayperiod":"Achaemenid Persian Period, ca. 550–330 BCE",
            "displaydate":"ca. 550–330 BCE"
        }
    ],
    "periodterms":[
        {
            "id":2037546,
            "period":"Achaemenid"
        }
    ],
    "dimensionelements":[
        {
            "element":"Overall",
            "type":"Height",
            "units":"centimeters",
            "dimension":"3.80"
        },
        {
            "element":"Overall",
            "type":"diam.",
            "units":"centimeters",
            "dimension":"15.00"
        }
    ],
    "packages":[],
    "primaryimage":[
        "https://media.artmuseum.princeton.edu/iiif/3/collection/INV65758"
    ],
    "displaymaker":null,
    "displayculture":null,
    "displayperiod":"Achaemenid Persian Period, ca. 550–330 BCE",
    "caption":"Achaemenid Persian Period (ca. 550–330 BCE), Bowl. Bronze; 3.8 × 15 cm. Museum purchase (y1959-4)",
    "captionhtml":"Achaemenid Persian Period (ca. 550–330 BCE), <i>Bowl</i>. Bronze; 3.8 × 15 cm. Museum purchase (y1959-4)",
    "published_date":"2025-10-23 17:06:46.536658",
    "campusart":[
        {
            "campuscollections":"false",
            "campusart":0,
            "neighborhood":null,
            "lat":null,
            "lon":null
        }
    ],
    "extended_content":false
}